{
    "status_code": 0,
    "data": {
        "info": [
            {
                "first_limit_up_time": "1776648303",
                "code": "688227",
                "order_volume": 0.0,
                "limit_up_suc_rate": 0.75,
                "sum_market_value": 13020576000.0,
                "461252": null,
                "last_limit_down_time": null,
                "order_amount": 0.0,
                "first_limit_down_time": null,
                "high_days_value": null,
                "rise_rate": 1.026,
                "turnover": 1918505900.0,
                "market_type": "STAR",
                "latest": 115.17,
                "open_num": 2,
                "last_limit_up_time": "1776649710",
                "limit_up_type": null,
                "is_new": 0,
                "currency_value": 13020576000.0,
                "market_id": 17,
                "is_again_limit": 0,
                "change_rate": 13.6247,
                "turnover_rate": 14.4335,
                "reason_type": null,
                "high_days": null,
                "name": "品高股份",
                "change_tag": "LIMIT_FAILED",
                "time_preview": [
                    19.998,
                    19.998,
                    19.998,
                    19.998,
                    19.998,
                    19.998,
                    19.998,
                    19.998,
                    14.0884,
                    13.0525,
                    13.457,
                    12.7664,
                    15.7557,
                    15.5485,
                    14.3646,
                    13.8319,
                    13.8516,
                    13.9503,
                    14.4436,
                    15.1835,
                    15.3118,
                    14.9961,
                    16.3082,
                    15.7261,
                    15.8248,
                    16.2194,
                    15.6275,
                    15.4992,
                    15.9136,
                    16.1701,
                    15.9136,
                    16.0024,
                    15.4893,
                    14.7593,
                    14.8875,
                    14.9862,
                    15.4301,
                    15.8346,
                    13.9009,
                    13.9601
                ]
            },
            {
                "first_limit_up_time": "1776649470",
                "code": "002428",
                "order_volume": 0.0,
                "limit_up_suc_rate": 0.6,
                "sum_market_value": 44497066000.0,
                "461252": null,
                "last_limit_down_time": null,
                "order_amount": 0.0,
                "first_limit_down_time": null,
                "high_days_value": null,
                "rise_rate": 0.044,
                "turnover": 5253043100.0,
                "market_type": "HS",
                "latest": 68.13,
                "open_num": 5,
                "last_limit_up_time": "1776655755",
                "limit_up_type": null,
                "is_new": 0,
                "currency_value": 44491317000.0,
                "market_id": 33,
                "is_again_limit": 0,
                "change_rate": 9.8871,
                "turnover_rate": 12.0664,
                "reason_type": null,
                "high_days": null,
                "name": "云南锗业",
                "change_tag": "LIMIT_FAILED",
                "time_preview": [
                    3.0,
                    7.0484,
                    7.9032,
                    8.1613,
                    9.4032,
                    9.6774,
                    9.9839,
                    10.0,
                    10.0,
                    10.0,
                    10.0,
                    10.0,
                    10.0,
                    10.0,
                    10.0,
                    10.0,
                    10.0,
                    10.0,
                    10.0,
                    10.0,
                    10.0,
                    10.0,
                    10.0,
                    10.0,
                    10.0,
                    10.0,
                    10.0,
                    10.0,
                    10.0,
                    10.0,
                    10.0,
                    10.0,
                    10.0,
                    10.0,
                    10.0,
                    10.0,
                    10.0,
                    10.0,
                    10.0,
                    8.629
                ]
            },
            {
                "first_limit_up_time": "1776650751",
                "code": "002837",
                "order_volume": 0.0,
                "limit_up_suc_rate": 0.5555555555555556,
                "sum_market_value": 118046073000.0,
                "461252": null,
                "last_limit_down_time": null,
                "order_amount": 0.0,
                "first_limit_down_time": null,
                "high_days_value": null,
                "rise_rate": 0.249,
                "turnover": 7442051900.0,
                "market_type": "HS",
                "latest": 120.88,
                "open_num": 2,
                "last_limit_up_time": "1776654195",
                "limit_up_type": null,
                "is_new": 0,
                "currency_value": 102771568000.0,
                "market_id": 33,
                "is_again_limit": 0,
                "change_rate": 9.2256,
                "turnover_rate": 7.3463,
                "reason_type": null,
                "high_days": null,
                "name": "英维克",
                "change_tag": "LIMIT_FAILED",
                "time_preview": [
                    2.2861,
                    3.4607,
                    4.0661,
                    5.8733,
                    7.3462,
                    7.0932,
                    7.3913,
                    7.6082,
                    8.6835,
                    9.0178,
                    9.1533,
                    9.9033,
                    9.9666,
                    10.0027,
                    10.0027,
                    10.0027,
                    10.0027,
                    10.0027,
                    10.0027,
                    10.0027,
                    10.0027,
                    10.0027,
                    10.0027,
                    10.0027,
                    10.0027,
                    10.0027,
                    10.0027,
                    10.0027,
                    10.0027,
                    10.0027,
                    10.0027,
                    10.0027,
                    8.8552,
                    9.2889,
                    9.0088,
                    9.0539,
                    8.4124,
                    8.3491,
                    8.5389,
                    8.9636
                ]
            },
            {
                "first_limit_up_time": "1776649398",
                "code": "000977",
                "order_volume": 0.0,
                "limit_up_suc_rate": 1.0,
                "sum_market_value": 107874295000.0,
                "461252": null,
                "last_limit_down_time": null,
                "order_amount": 0.0,
                "first_limit_down_time": null,
                "high_days_value": null,
                "rise_rate": 0.0,
                "turnover": 8821566800.0,
                "market_type": "HS",
                "latest": 73.46,
                "open_num": 2,
                "last_limit_up_time": "1776651162",
                "limit_up_type": null,
                "is_new": 0,
                "currency_value": 107753464000.0,
                "market_id": 33,
                "is_again_limit": 0,
                "change_rate": 7.6652,
                "turnover_rate": 8.135,
                "reason_type": null,
                "high_days": null,
                "name": "浪潮信息",
                "change_tag": "LIMIT_FAILED",
                "time_preview": [
                    1.7881,
                    6.4195,
                    6.9178,
                    9.2921,
                    9.1895,
                    9.7758,
                    9.8344,
                    9.2921,
                    9.0576,
                    8.911,
                    8.7938,
                    8.955,
                    8.9697,
                    9.8784,
                    9.9956,
                    8.9697,
                    8.911,
                    8.5153,
                    8.5593,
                    8.2808,
                    8.6326,
                    8.5446,
                    9.2628,
                    8.7205,
                    8.2808,
                    8.1489,
                    7.9291,
                    8.1636,
                    8.1196,
                    8.2222,
                    8.0903,
                    8.3394,
                    8.1049,
                    7.7532,
                    7.548,
                    7.2549,
                    7.1083,
                    7.079,
                    7.2109,
                    7.4454
                ]
            },
            {
                "first_limit_up_time": "1776648873",
                "code": "003041",
                "order_volume": 0.0,
                "limit_up_suc_rate": 0.6111111111111112,
                "sum_market_value": 8938080000.0,
                "461252": null,
                "last_limit_down_time": null,
                "order_amount": 0.0,
                "first_limit_down_time": null,
                "high_days_value": null,
                "rise_rate": 0.258,
                "turnover": 445550430.0,
                "market_type": "HS",
                "latest": 62.07,
                "open_num": 1,
                "last_limit_up_time": "1776651045",
                "limit_up_type": null,
                "is_new": 0,
                "currency_value": 8492628400.0,
                "market_id": 33,
                "is_again_limit": 0,
                "change_rate": 7.4247,
                "turnover_rate": 5.2139,
                "reason_type": null,
                "high_days": null,
                "name": "真爱美家",
                "change_tag": "LIMIT_FAILED",
                "time_preview": [
                    4.9671,
                    8.3593,
                    10.0035,
                    10.0035,
                    10.0035,
                    10.0035,
                    10.0035,
                    10.0035,
                    10.0035,
                    10.0035,
                    10.0035,
                    10.0035,
                    10.0035,
                    10.0035,
                    8.74,
                    8.0824,
                    8.0997,
                    8.3247,
                    7.9093,
                    7.6151,
                    8.0651,
                    9.8131,
                    8.6362,
                    8.6016,
                    8.6016,
                    8.0305,
                    7.8228,
                    7.9958,
                    7.8055,
                    8.3593,
                    7.8228,
                    7.5112,
                    6.6632,
                    6.6113,
                    6.4555,
                    7.3209,
                    7.1997,
                    7.6151,
                    7.2516,
                    6.992
                ]
            },
            {
                "first_limit_up_time": "1776652361",
                "code": "603052",
                "order_volume": 0.0,
                "limit_up_suc_rate": 0.7619047619047619,
                "sum_market_value": 16722858000.0,
                "461252": null,
                "last_limit_down_time": null,
                "order_amount": 0.0,
                "first_limit_down_time": null,
                "high_days_value": null,
                "rise_rate": 0.135,
                "turnover": 1259854360.0,
                "market_type": "HS",
                "latest": 89.0,
                "open_num": 2,
                "last_limit_up_time": "1776652457",
                "limit_up_type": null,
                "is_new": 0,
                "currency_value": 16722858000.0,
                "market_id": 17,
                "is_again_limit": 0,
                "change_rate": 6.7786,
                "turnover_rate": 7.6038,
                "reason_type": null,
                "high_days": null,
                "name": "可川科技",
                "change_tag": "LIMIT_FAILED",
                "time_preview": [
                    4.799,
                    2.0156,
                    2.5795,
                    4.3911,
                    4.2591,
                    4.3071,
                    3.7552,
                    4.3791,
                    2.9994,
                    4.871,
                    5.099,
                    5.6869,
                    6.6707,
                    7.5465,
                    6.7307,
                    6.0468,
                    6.0108,
                    8.8902,
                    7.9304,
                    8.0984,
                    8.7582,
                    9.5381,
                    8.6983,
                    8.9142,
                    8.2903,
                    8.1464,
                    8.0984,
                    8.0864,
                    7.8584,
                    7.9664,
                    8.1224,
                    7.9664,
                    6.7906,
                    6.5387,
                    6.3467,
                    6.4427,
                    6.2987,
                    6.0228,
                    5.9988,
                    6.4907
                ]
            },
            {
                "first_limit_up_time": "1776648924",
                "code": "000778",
                "order_volume": 0.0,
                "limit_up_suc_rate": 0.0,
                "sum_market_value": 18864748000.0,
                "461252": null,
                "last_limit_down_time": null,
                "order_amount": 0.0,
                "first_limit_down_time": null,
                "high_days_value": null,
                "rise_rate": -0.21,
                "turnover": 607262730.0,
                "market_type": "HS",
                "latest": 4.76,
                "open_num": 1,
                "last_limit_up_time": "1776648936",
                "limit_up_type": null,
                "is_new": 0,
                "currency_value": 18533157000.0,
                "market_id": 33,
                "is_again_limit": 0,
                "change_rate": 6.7265,
                "turnover_rate": 3.2522,
                "reason_type": null,
                "high_days": null,
                "name": "新兴铸管",
                "change_tag": "LIMIT_FAILED",
                "time_preview": [
                    1.7937,
                    7.3991,
                    10.0897,
                    9.6413,
                    7.1749,
                    6.7265,
                    6.5022,
                    8.296,
                    8.5202,
                    7.8475,
                    7.3991,
                    6.9507,
                    6.9507,
                    7.3991,
                    7.1749,
                    6.9507,
                    6.9507,
                    8.0717,
                    7.6233,
                    7.3991,
                    7.3991,
                    6.9507,
                    7.1749,
                    6.9507,
                    6.9507,
                    6.7265,
                    6.7265,
                    6.7265,
                    6.9507,
                    6.7265,
                    6.278,
                    6.278,
                    6.7265,
                    6.9507,
                    6.9507,
                    6.7265,
                    6.7265,
                    6.5022,
                    6.5022,
                    6.7265
                ]
            },
            {
                "first_limit_up_time": "1776651858",
                "code": "001896",
                "order_volume": 0.0,
                "limit_up_suc_rate": 0.7647058823529411,
                "sum_market_value": 27448806000.0,
                "461252": null,
                "last_limit_down_time": null,
                "order_amount": 0.0,
                "first_limit_down_time": null,
                "high_days_value": null,
                "rise_rate": 0.167,
                "turnover": 3409849800.0,
                "market_type": "HS",
                "latest": 17.99,
                "open_num": 3,
                "last_limit_up_time": "1776651966",
                "limit_up_type": null,
                "is_new": 0,
                "currency_value": 27448806000.0,
                "market_id": 33,
                "is_again_limit": 0,
                "change_rate": 5.3279,
                "turnover_rate": 12.5011,
                "reason_type": null,
                "high_days": null,
                "name": "豫能控股",
                "change_tag": "LIMIT_FAILED",
                "time_preview": [
                    1.4052,
                    3.8642,
                    5.9719,
                    3.3372,
                    -0.4684,
                    0.9953,
                    0.4684,
                    0.8782,
                    0.2342,
                    0.4098,
                    0.4684,
                    0.8197,
                    0.3513,
                    1.3466,
                    2.2248,
                    3.6885,
                    3.8056,
                    7.3185,
                    6.6159,
                    7.9625,
                    7.7283,
                    7.26,
                    7.6112,
                    7.2014,
                    6.9087,
                    6.9672,
                    7.1429,
                    6.9672,
                    7.377,
                    7.1429,
                    6.3817,
                    6.0304,
                    6.2061,
                    6.0304,
                    5.5621,
                    5.8548,
                    5.2693,
                    5.0351,
                    4.9766,
                    5.0937
                ]
            },
            {
                "first_limit_up_time": "1776649350",
                "code": "002962",
                "order_volume": 0.0,
                "limit_up_suc_rate": 1.0,
                "sum_market_value": 5299559400.0,
                "461252": null,
                "last_limit_down_time": null,
                "order_amount": 0.0,
                "first_limit_down_time": null,
                "high_days_value": null,
                "rise_rate": -0.11,
                "turnover": 726870470.0,
                "market_type": "HS",
                "latest": 18.17,
                "open_num": 2,
                "last_limit_up_time": "1776649707",
                "limit_up_type": null,
                "is_new": 0,
                "currency_value": 3800873400.0,
                "market_id": 33,
                "is_again_limit": 0,
                "change_rate": 4.7262,
                "turnover_rate": 18.9491,
                "reason_type": null,
                "high_days": null,
                "name": "五方光电",
                "change_tag": "LIMIT_FAILED",
                "time_preview": [
                    0.2305,
                    1.6138,
                    1.4986,
                    2.8818,
                    7.6081,
                    10.0288,
                    10.0288,
                    10.0288,
                    6.6282,
                    7.4352,
                    7.3199,
                    6.1671,
                    4.0346,
                    5.5908,
                    4.6686,
                    5.7637,
                    5.8213,
                    4.4957,
                    5.072,
                    4.8415,
                    5.4755,
                    6.3401,
                    6.1095,
                    6.513,
                    6.4553,
                    6.3977,
                    5.0144,
                    5.0144,
                    5.072,
                    5.1873,
                    4.9568,
                    5.879,
                    5.245,
                    5.4755,
                    5.5331,
                    5.4755,
                    5.4755,
                    5.0144,
                    5.0144,
                    4.7262
                ]
            },
            {
                "first_limit_up_time": "1776651930",
                "code": "002058",
                "order_volume": 0.0,
                "limit_up_suc_rate": 0.5789473684210527,
                "sum_market_value": 3280663400.0,
                "461252": null,
                "last_limit_down_time": null,
                "order_amount": 0.0,
                "first_limit_down_time": null,
                "high_days_value": null,
                "rise_rate": -0.044,
                "turnover": 67936247.0,
                "market_type": "HS",
                "latest": 22.87,
                "open_num": 8,
                "last_limit_up_time": "1776654480",
                "limit_up_type": null,
                "is_new": 0,
                "currency_value": 3273103700.0,
                "market_id": 33,
                "is_again_limit": 0,
                "change_rate": 4.5247,
                "turnover_rate": 2.0917,
                "reason_type": null,
                "high_days": null,
                "name": "*ST威尔",
                "change_tag": "LIMIT_FAILED",
                "time_preview": [
                    0.457,
                    0.5027,
                    0.6856,
                    0.6399,
                    0.4113,
                    0.457,
                    0.4113,
                    0.1828,
                    0.2742,
                    -0.1371,
                    -0.0914,
                    1.2797,
                    1.1426,
                    1.5996,
                    1.9196,
                    2.6965,
                    2.6965,
                    3.4278,
                    3.3364,
                    4.4333,
                    4.5247,
                    4.7989,
                    4.936,
                    4.936,
                    4.9817,
                    4.9817,
                    4.9817,
                    4.936,
                    4.936,
                    4.8903,
                    4.9817,
                    4.9817,
                    4.9817,
                    4.8903,
                    4.6161,
                    4.7989,
                    4.6618,
                    4.6618,
                    4.6618,
                    4.6618
                ]
            },
            {
                "first_limit_up_time": "1776653757",
                "code": "603021",
                "order_volume": 0.0,
                "limit_up_suc_rate": 0.6363636363636364,
                "sum_market_value": 2610776300.0,
                "461252": null,
                "last_limit_down_time": null,
                "order_amount": 0.0,
                "first_limit_down_time": null,
                "high_days_value": null,
                "rise_rate": -0.488,
                "turnover": 72750821.0,
                "market_type": "HS",
                "latest": 8.16,
                "open_num": 2,
                "last_limit_up_time": "1776655635",
                "limit_up_type": null,
                "is_new": 0,
                "currency_value": 2610776300.0,
                "market_id": 22,
                "is_again_limit": 0,
                "change_rate": 4.3478,
                "turnover_rate": 2.8041,
                "reason_type": null,
                "high_days": null,
                "name": "ST华鹏",
                "change_tag": "LIMIT_FAILED",
                "time_preview": [
                    2.3018,
                    3.8363,
                    3.0691,
                    2.8133,
                    2.5575,
                    2.4297,
                    2.5575,
                    2.6854,
                    3.1969,
                    2.8133,
                    2.8133,
                    3.3248,
                    3.1969,
                    3.1969,
                    3.1969,
                    3.1969,
                    3.3248,
                    3.1969,
                    3.3248,
                    3.3248,
                    3.3248,
                    3.1969,
                    2.9412,
                    2.8133,
                    2.8133,
                    3.0691,
                    3.7084,
                    3.7084,
                    3.8363,
                    4.9872,
                    4.8593,
                    4.9872,
                    4.9872,
                    4.9872,
                    4.9872,
                    4.9872,
                    4.9872,
                    4.9872,
                    4.9872,
                    4.9872
                ]
            },
            {
                "first_limit_up_time": "1776651363",
                "code": "003004",
                "order_volume": 0.0,
                "limit_up_suc_rate": 0.8,
                "sum_market_value": 2723563500.0,
                "461252": null,
                "last_limit_down_time": null,
                "order_amount": 0.0,
                "first_limit_down_time": null,
                "high_days_value": null,
                "rise_rate": 0.271,
                "turnover": 31029757.0,
                "market_type": "HS",
                "latest": 33.27,
                "open_num": 1,
                "last_limit_up_time": "1776651618",
                "limit_up_type": null,
                "is_new": 0,
                "currency_value": 2287027000.0,
                "market_id": 33,
                "is_again_limit": 0,
                "change_rate": 4.1641,
                "turnover_rate": 1.3625,
                "reason_type": null,
                "high_days": null,
                "name": "*ST声迅",
                "change_tag": "LIMIT_FAILED",
                "time_preview": [
                    0.0313,
                    3.3187,
                    2.7239,
                    2.943,
                    2.6925,
                    2.1916,
                    2.3795,
                    2.943,
                    3.35,
                    3.3813,
                    3.8823,
                    4.2893,
                    4.258,
                    4.6337,
                    4.6337,
                    4.2893,
                    4.2893,
                    5.0094,
                    5.0094,
                    4.2893,
                    4.1954,
                    4.1014,
                    4.3832,
                    4.4458,
                    4.4458,
                    4.4458,
                    4.3832,
                    4.1954,
                    4.1327,
                    4.1954,
                    4.1327,
                    4.1327,
                    4.1014,
                    4.0701,
                    4.0388,
                    3.9449,
                    3.8197,
                    3.6631,
                    3.6631,
                    3.6318
                ]
            },
            {
                "first_limit_up_time": "1776649653",
                "code": "000929",
                "order_volume": 0.0,
                "limit_up_suc_rate": 0.65,
                "sum_market_value": 1970977300.0,
                "461252": null,
                "last_limit_down_time": null,
                "order_amount": 0.0,
                "first_limit_down_time": null,
                "high_days_value": null,
                "rise_rate": 0.0,
                "turnover": 42121705.0,
                "market_type": "HS",
                "latest": 10.61,
                "open_num": 2,
                "last_limit_up_time": "1776651954",
                "limit_up_type": null,
                "is_new": 0,
                "currency_value": 1970852300.0,
                "market_id": 33,
                "is_again_limit": 0,
                "change_rate": 4.1217,
                "turnover_rate": 2.1439,
                "reason_type": null,
                "high_days": null,
                "name": "*ST兰黄",
                "change_tag": "LIMIT_FAILED",
                "time_preview": [
                    1.0795,
                    0.9814,
                    1.8646,
                    2.8459,
                    2.9441,
                    3.3366,
                    3.5329,
                    4.5142,
                    4.1217,
                    4.2198,
                    4.5142,
                    4.318,
                    4.318,
                    4.6124,
                    4.5142,
                    4.5142,
                    4.5142,
                    5.0049,
                    5.0049,
                    5.0049,
                    5.0049,
                    4.6124,
                    4.8086,
                    4.9068,
                    4.9068,
                    4.8086,
                    4.2198,
                    4.2198,
                    4.2198,
                    4.0236,
                    4.318,
                    4.318,
                    4.318,
                    4.318,
                    4.318,
                    4.1217,
                    4.0236,
                    4.0236,
                    4.2198,
                    4.1217
                ]
            },
            {
                "first_limit_up_time": "1776649131",
                "code": "002528",
                "order_volume": 0.0,
                "limit_up_suc_rate": 0.6842105263157895,
                "sum_market_value": 6448871900.0,
                "461252": null,
                "last_limit_down_time": null,
                "order_amount": 0.0,
                "first_limit_down_time": null,
                "high_days_value": null,
                "rise_rate": 0.938,
                "turnover": 323245990.0,
                "market_type": "HS",
                "latest": 5.38,
                "open_num": 5,
                "last_limit_up_time": "1776654396",
                "limit_up_type": null,
                "is_new": 0,
                "currency_value": 5650181300.0,
                "market_id": 33,
                "is_again_limit": 0,
                "change_rate": 0.0,
                "turnover_rate": 5.5316,
                "reason_type": null,
                "high_days": null,
                "name": "ST英飞拓",
                "change_tag": "LIMIT_FAILED",
                "time_preview": [
                    4.461,
                    2.4164,
                    2.2305,
                    4.461,
                    4.0892,
                    3.3457,
                    2.974,
                    3.5316,
                    3.7175,
                    3.1599,
                    2.974,
                    3.9033,
                    3.1599,
                    3.3457,
                    3.3457,
                    3.1599,
                    3.1599,
                    4.2751,
                    4.0892,
                    3.9033,
                    4.2751,
                    4.6468,
                    5.0186,
                    5.0186,
                    5.0186,
                    4.2751,
                    5.0186,
                    4.8327,
                    4.8327,
                    5.0186,
                    4.6468,
                    4.8327,
                    5.0186,
                    4.6468,
                    4.8327,
                    4.2751,
                    3.3457,
                    2.0446,
                    1.3011,
                    0.9294
                ]
            },
            {
                "first_limit_up_time": "1776648723",
                "code": "002940",
                "order_volume": 0.0,
                "limit_up_suc_rate": 0.8846153846153846,
                "sum_market_value": 7812932600.0,
                "461252": null,
                "last_limit_down_time": null,
                "order_amount": 0.0,
                "first_limit_down_time": null,
                "high_days_value": null,
                "rise_rate": -0.743,
                "turnover": 2088685000.0,
                "market_type": "HS",
                "latest": 38.73,
                "open_num": 2,
                "last_limit_up_time": "1776648738",
                "limit_up_type": null,
                "is_new": 0,
                "currency_value": 7175718800.0,
                "market_id": 33,
                "is_again_limit": 0,
                "change_rate": -1.0981,
                "turnover_rate": 27.3665,
                "reason_type": null,
                "high_days": null,
                "name": "昂利康",
                "change_tag": "LIMIT_FAILED",
                "time_preview": [
                    7.5077,
                    9.3718,
                    8.1716,
                    7.0991,
                    4.7497,
                    3.0899,
                    4.6221,
                    3.856,
                    4.6731,
                    3.192,
                    3.0644,
                    2.3749,
                    2.5281,
                    2.2472,
                    2.145,
                    1.8386,
                    1.8386,
                    1.5832,
                    1.5577,
                    1.5832,
                    0.332,
                    -0.3575,
                    0.2809,
                    0.0255,
                    -0.332,
                    0.8682,
                    -0.2043,
                    -0.6384,
                    -0.4852,
                    -0.4852,
                    -1.2768,
                    -1.6854,
                    -0.9448,
                    -1.047,
                    -1.1236,
                    -1.762,
                    -1.2768,
                    -1.9408,
                    -1.4045,
                    -0.2298
                ]
            }
        ],
        "business_date": "20260420"
    }
}