{
  "lastUpdate": "2025-11-04T19:18:41.621847",
  "newsCount": 1984,
  "dateRange": {
    "start": "2025-10-31",
    "end": "2025-11-04"
  },
  "topKeywords": [
    {
      "date": "2025-11-04",
      "keyword": "机器人",
      "positive": 3,
      "negative": 0,
      "neutral": 9
    },
    {
      "date": "2025-11-04",
      "keyword": "军工",
      "positive": 1,
      "negative": 0,
      "neutral": 1
    },
    {
      "date": "2025-11-04",
      "keyword": "算力",
      "positive": 2,
      "negative": 0,
      "neutral": 2
    },
    {
      "date": "2025-11-04",
      "keyword": "芯片",
      "positive": 1,
      "negative": 0,
      "neutral": 3
    },
    {
      "date": "2025-11-04",
      "keyword": "半导体",
      "positive": 3,
      "negative": 0,
      "neutral": 4
    },
    {
      "date": "2025-11-04",
      "keyword": "新能源",
      "positive": 2,
      "negative": 0,
      "neutral": 3
    },
    {
      "date": "2025-11-04",
      "keyword": "人工智能",
      "positive": 4,
      "negative": 1,
      "neutral": 3
    },
    {
      "date": "2025-11-04",
      "keyword": "无人机",
      "positive": 0,
      "negative": 0,
      "neutral": 2
    },
    {
      "date": "2025-11-03",
      "keyword": "算力",
      "positive": 1,
      "negative": 0,
      "neutral": 7
    },
    {
      "date": "2025-11-03",
      "keyword": "芯片",
      "positive": 4,
      "negative": 0,
      "neutral": 10
    }
  ],
  "topStocks": [
    [
      "英伟达",
      33
    ],
    [
      "谷歌",
      10
    ],
    [
      "京东",
      9
    ],
    [
      "阿里巴巴",
      8
    ],
    [
      "比亚迪",
      8
    ],
    [
      "小米",
      6
    ],
    [
      "华为",
      5
    ],
    [
      "中际旭创",
      5
    ],
    [
      "理想汽车",
      4
    ],
    [
      "网易",
      2
    ],
    [
      "TCL",
      2
    ],
    [
      "宁德时代",
      2
    ],
    [
      "腾讯",
      2
    ]
  ]
}